pandaserd/VERSION
pandaserd/__init__.py
pandaserd/module.py
pandaserd/version.py
pandaserd-0.1.5.dist-info/LICENSE.txt
pandaserd-0.1.5.dist-info/METADATA
pandaserd-0.1.5.dist-info/WHEEL
pandaserd-0.1.5.dist-info/top_level.txt
pandaserd-0.1.5.dist-info/RECORD
