Metadata-Version: 2.1
Name: pandaserd
Version: 0.1.5
Summary: Create ERD/data flow diagrams from pandas dataframes.
Home-page: https://github.com/nabsabraham/pandas-erd
Author: Nabila Abraham
Author-email: nabila.abraham@gmail.com
License: UNKNOWN
Platform: UNKNOWN
Requires-Python: >=3.6
Requires-Dist: pandas
